b3futurecontracts.py
b3futurecontracts-0.0.7.dist-info/LICENSE
b3futurecontracts-0.0.7.dist-info/METADATA
b3futurecontracts-0.0.7.dist-info/WHEEL
b3futurecontracts-0.0.7.dist-info/top_level.txt
b3futurecontracts-0.0.7.dist-info/RECORD
