Metadata-Version: 2.1
Name: b3futurecontracts
Version: 0.0.7
Summary: Rollover date of future contracts from the B3 exchange
Home-page: https://github.com/alvfig/b3futurecontracts
Author: Alvaro Figueiredo
Author-email: alvaro.af@gmail.com
License: UNKNOWN
Platform: UNKNOWN
Classifier: Programming Language :: Python :: 3
Classifier: License :: OSI Approved :: MIT License
Classifier: Operating System :: OS Independent
Requires-Python: >=3
